thinkgpt/__init__.py
thinkgpt/abstract.py
thinkgpt/condition.py
thinkgpt/gpt_select.py
thinkgpt/helper.py
thinkgpt/infer.py
thinkgpt/llm.py
thinkgpt/memory.py
thinkgpt/refine.py
thinkgpt/summarize.py
thinkgpt-0.0.6.dist-info/LICENSE
thinkgpt-0.0.6.dist-info/METADATA
thinkgpt-0.0.6.dist-info/WHEEL
thinkgpt-0.0.6.dist-info/RECORD
