Metadata-Version: 2.1
Name: thinkgpt
Version: 0.0.6
Summary: ThinkGPT is a Python library aimed at implementing Chain of Thoughts for Large Language Models (LLMs), prompting the model to think, reason, and to create generative agents.
License: Apache 2.0
Author: Alaeddine Abdessalem
Author-email: alaeddine-13@live.fr
Requires-Python: >=3.7,<4.0
Classifier: License :: Other/Proprietary License
Classifier: Programming Language :: Python :: 3
Classifier: Programming Language :: Python :: 3.7
Classifier: Programming Language :: Python :: 3.8
Classifier: Programming Language :: Python :: 3.9
Classifier: Programming Language :: Python :: 3.10
Classifier: Programming Language :: Python :: 3.11
Requires-Dist: docarray (<=0.21.0)
Requires-Dist: langchain (>=0.0.141,<0.0.142)
Requires-Dist: openai (>=0.27.4,<0.28.0)
Requires-Dist: tiktoken (>=0.3.3,<0.4.0)
